ngilive/__init__.py
ngilive/api.py
ngilive/auth.py
ngilive/config.py
ngilive/httpx_wrapper.py
ngilive/log.py
ngilive/schema.py
ngilive/terminal_helpers.py
ngilive-0.5.7.dist-info/METADATA
ngilive-0.5.7.dist-info/WHEEL
ngilive-0.5.7.dist-info/RECORD
