Metadata-Version: 2.3
Name: ngilive
Version: 0.5.7
Summary: 
Author: Ole-Jakob Olsen
Author-email: ole.jakob.olsen@ngi.no
Requires-Python: >=3.11,<4.0
Classifier: Programming Language :: Python :: 3
Classifier: Programming Language :: Python :: 3.11
Classifier: Programming Language :: Python :: 3.12
Classifier: Programming Language :: Python :: 3.13
Requires-Dist: httpx (>=0.28.1,<0.29.0)
Requires-Dist: pydantic (>=2.11.9,<3.0.0)
